getcleftpy/__init__.py
getcleftpy/bin/GetCleft.exe
getcleftpy/GetCleft_wrapper.py
getcleft_py-1.0.5.dist-info/METADATA
getcleft_py-1.0.5.dist-info/WHEEL
getcleft_py-1.0.5.dist-info/RECORD
