Metadata-Version: 2.2
Name: getcleft-py
Version: 1.0.5
Summary: Python wheels and a wrapper for GetCleft, a tool to find clefts in PDB files
Author: Thomas DesCôteaux
Author-Email: Rafael Najmanovich <rafael.najmanovich@umontreal.ca>
Classifier: Intended Audience :: Science/Research
Classifier: License :: OSI Approved :: GNU General Public License v3 or later (GPLv3+)
Classifier: Natural Language :: English
Project-URL: Homepage, https://github.com/NRGlab
Project-URL: Documentation, https://github.com/NRGlab/getcleft-py/blob/main/README.md
Project-URL: Repository, https://github.com/NRGlab/getcleft-py
Project-URL: Issues, https://github.com/NRGlab/getcleft-py/issues
Requires-Python: >=3.9
